iotopen_bridge/__about__.py
iotopen_bridge/__init__.py
iotopen_bridge/__main__.py
iotopen_bridge/py.typed
iotopen_bridge/adapters/__init__.py
iotopen_bridge/adapters/discovery_state.py
iotopen_bridge/adapters/ha_discovery_publisher.py
iotopen_bridge/adapters/ha_native_publisher.py
iotopen_bridge/adapters/ha_service_adapter.py
iotopen_bridge/adapters/mqtt_router.py
iotopen_bridge/adapters/raw_capture.py
iotopen_bridge/api/__init__.py
iotopen_bridge/api/app.py
iotopen_bridge/api/auth.py
iotopen_bridge/api/routes/__init__.py
iotopen_bridge/api/routes/commands.py
iotopen_bridge/api/routes/health.py
iotopen_bridge/api/routes/inventory.py
iotopen_bridge/bridge/__init__.py
iotopen_bridge/bridge/config.py
iotopen_bridge/bridge/health.py
iotopen_bridge/bridge/health_http.py
iotopen_bridge/bridge/profiles.py
iotopen_bridge/bridge/runtime.py
iotopen_bridge/bridge/supervisor.py
iotopen_bridge/cli/__init__.py
iotopen_bridge/cli/main.py
iotopen_bridge/cli/run_supervised.py
iotopen_bridge/cli/commands/__init__.py
iotopen_bridge/cli/commands/dump_inventory.py
iotopen_bridge/cli/commands/dynsec_apply.py
iotopen_bridge/cli/commands/init_config.py
iotopen_bridge/cli/commands/probe_api.py
iotopen_bridge/cli/commands/probe_mqtt.py
iotopen_bridge/cli/commands/rotate_keys.py
iotopen_bridge/cli/commands/run.py
iotopen_bridge/cli/commands/show_acl.py
iotopen_bridge/controllers/__init__.py
iotopen_bridge/controllers/commands.py
iotopen_bridge/controllers/inventory.py
iotopen_bridge/controllers/reconciliation.py
iotopen_bridge/controllers/scheduler.py
iotopen_bridge/controllers/telemetry.py
iotopen_bridge/converters/__init__.py
iotopen_bridge/converters/ha_discovery/__init__.py
iotopen_bridge/converters/ha_discovery/builder.py
iotopen_bridge/converters/ha_discovery/topics.py
iotopen_bridge/converters/mapping/__init__.py
iotopen_bridge/converters/mapping/entities.py
iotopen_bridge/converters/mapping/function_to_entity.py
iotopen_bridge/converters/mapping/function_to_topics.py
iotopen_bridge-0.1.7.dist-info/licenses/LICENSE
iotopen_bridge-0.1.7.dist-info/METADATA
iotopen_bridge-0.1.7.dist-info/WHEEL
iotopen_bridge-0.1.7.dist-info/entry_points.txt
iotopen_bridge-0.1.7.dist-info/top_level.txt
iotopen_bridge-0.1.7.dist-info/RECORD
